swipe_verse/__init__.py
swipe_verse/__main__.py
swipe_verse/cli_launcher.py
swipe_verse/main.py
swipe_verse/assets/default/card_back.png
swipe_verse/assets/default/card_fronts/challenge.png
swipe_verse/assets/default/card_fronts/choice.png
swipe_verse/assets/default/card_fronts/event.png
swipe_verse/assets/default/card_fronts/oppurtunity.png
swipe_verse/assets/default/resource_icons/harmony.png
swipe_verse/assets/default/resource_icons/people.png
swipe_verse/assets/default/resource_icons/power.png
swipe_verse/assets/default/resource_icons/resource.png
swipe_verse/assets/themes/business/card_back.png
swipe_verse/assets/themes/business/card_fronts/acquisition.png
swipe_verse/assets/themes/business/card_fronts/budget_cuts.png
swipe_verse/assets/themes/business/card_fronts/marketing.png
swipe_verse/assets/themes/business/card_fronts/remote_work.png
swipe_verse/assets/themes/business/resource_icons/employees.png
swipe_verse/assets/themes/business/resource_icons/finances.png
swipe_verse/assets/themes/business/resource_icons/innovation.png
swipe_verse/assets/themes/business/resource_icons/reputation.png
swipe_verse/assets/themes/medieval/card_back.png
swipe_verse/assets/themes/medieval/card_fronts/foreign_envoy.png
swipe_verse/assets/themes/medieval/card_fronts/harvest.png
swipe_verse/assets/themes/medieval/card_fronts/military_training.png
swipe_verse/assets/themes/medieval/card_fronts/religious_festival.png
swipe_verse/assets/themes/medieval/resource_icons/church.png
swipe_verse/assets/themes/medieval/resource_icons/military.png
swipe_verse/assets/themes/medieval/resource_icons/population.png
swipe_verse/assets/themes/medieval/resource_icons/treasury.png
swipe_verse/models/__init__.py
swipe_verse/models/card.py
swipe_verse/models/config.py
swipe_verse/models/game_state.py
swipe_verse/models/resource.py
swipe_verse/scenarios/LICENSE
swipe_verse/scenarios/__init__.py
swipe_verse/scenarios/business_game.json
swipe_verse/scenarios/kingdom_game.json
swipe_verse-0.1.10.dist-info/METADATA
swipe_verse-0.1.10.dist-info/WHEEL
swipe_verse-0.1.10.dist-info/entry_points.txt
swipe_verse-0.1.10.dist-info/licenses/AUTHORS.md
swipe_verse-0.1.10.dist-info/licenses/LICENSE
swipe_verse-0.1.10.dist-info/RECORD
