Metadata-Version: 2.4
Name: swipe-verse
Version: 0.1.10
Summary: A multiverse card-based decision game with themes across different realities
Author: Michael
License: MIT
License-File: AUTHORS.md
License-File: LICENSE
Requires-Python: >=3.10
Requires-Dist: aiohttp>=3.8.0
Requires-Dist: flet>=0.27.0
Requires-Dist: pillow>=9.0.0
Requires-Dist: pydantic>=2.0.0
Provides-Extra: dev
Requires-Dist: mkdocs-material>=8.2.0; extra == 'dev'
Requires-Dist: mkdocs>=1.3.0; extra == 'dev'
Requires-Dist: mypy>=1.0.0; extra == 'dev'
Requires-Dist: pytest-asyncio>=0.18.0; extra == 'dev'
Requires-Dist: pytest-cov>=4.1.0; extra == 'dev'
Requires-Dist: pytest-mock>=3.10.0; extra == 'dev'
Requires-Dist: pytest>=7.0.0; extra == 'dev'
Requires-Dist: ruff>=0.0.230; extra == 'dev'
